Metadata-Version: 1.0
Name: MysqlDiff
Version: 1.3
Summary: mysql表结构比较工具
Home-page: https://github.com/icecooly/MysqlDiff
Author: skydu
Author-email: icecooly.du@qq.com
License: MIT
Keywords: mysql diff
Platform: UNKNOWN
